weback_unofficial/__init__.py
weback_unofficial/client.py
weback_unofficial/vacuum.py
weback_unofficial-0.3.5.dist-info/LICENSE
weback_unofficial-0.3.5.dist-info/METADATA
weback_unofficial-0.3.5.dist-info/WHEEL
weback_unofficial-0.3.5.dist-info/top_level.txt
weback_unofficial-0.3.5.dist-info/RECORD
