Metadata-Version: 2.1
Name: weback-unofficial
Version: 0.3.5
Summary: Unofficial client for WeBack API
Home-page: https://github.com/opravdin/weback-unofficial
Author: Pravdin Oleg
Author-email: opravdin@gmail.com
License: UNKNOWN
Platform: UNKNOWN
Classifier: Programming Language :: Python :: 3
Classifier: License :: OSI Approved :: MIT License
Classifier: Operating System :: OS Independent
Requires-Python: >=3.7
